[
    {
        "user_id": "3",
        "pg_question_id": "1",
        "answer": "E",
        "correct": true
    },
    {
        "user_id": "3",
        "pg_question_id": "2",
        "answer": "C",
        "correct": true
    },
    {
        "user_id": "4",
        "pg_question_id": "3",
        "answer": "D",
        "correct": true
    },
    {
        "user_id": "4",
        "pg_question_id": "4",
        "answer": "B",
        "correct": true
    },
    {
        "user_id": "4",
        "pg_question_id": "5",
        "answer": "B",
        "correct": false
    }
]